brain.py
duplicate_tools.py
experience.py
json_mage.py
loops.py
simple_file.py
tool_fluency.py
tool_fluency_v2.py
dragohan_grimoire-7.0.0.dist-info/licenses/LICENSE
experience_data/__init__.py
internet/__init__.py
internet/converter.py
internet/getter.py
internet/getter10.py
internet/getter8.py
internet/getter9.py
monarchs/__init__.py
monarchs/core.py
monarchs/data.py
monarchs/factory.py
monarchs/lead.py
monarchs/registry.py
monarchs/restaurant.py
monarchs/norgans/__init__.py
monarchs/norgans/helpers/__init__.py
monarchs/norgans/helpers/data_mapper.py
monarchs/norgans/helpers/file_writer.py
monarchs/norgans/helpers/phone_validator.py
monarchs/systems/__init__.py
monarchs/systems/base.py
monarchs/systems/data_system.py
monarchs/systems/norgan_base.py
monarchs/systems/personalisation_system_updated.py
monarchs/systems/registry.py
dragohan_grimoire-7.0.0.dist-info/METADATA
dragohan_grimoire-7.0.0.dist-info/WHEEL
dragohan_grimoire-7.0.0.dist-info/entry_points.txt
dragohan_grimoire-7.0.0.dist-info/top_level.txt
dragohan_grimoire-7.0.0.dist-info/RECORD
