Metadata-Version: 2.4
Name: dragohan-grimoire
Version: 7.0.0
Summary: 💀 AI Automation Grimoire v2.1.0 - PRODUCTION with Fixed Monarch System
Home-page: https://github.com/farhanistopG1/my_grimoire
Author: DragoHan
Author-email: aafr0408@gmail.com
Project-URL: Bug Tracker, https://github.com/farhanistopG1/my_grimoire/issues
Project-URL: Source Code, https://github.com/farhanistopG1/my_grimoire
Project-URL: Documentation, https://github.com/farhanistopG1/my_grimoire/wiki
Keywords: json,files,automation,api,ai,agents,langchain,llm,deepseek,shadow-monarch,lead-enrichment,data-processing
Classifier: Programming Language :: Python :: 3
Classifier: Programming Language :: Python :: 3.8
Classifier: Programming Language :: Python :: 3.9
Classifier: Programming Language :: Python :: 3.10
Classifier: Programming Language :: Python :: 3.11
Classifier: Programming Language :: Python :: 3.12
Classifier: License :: OSI Approved :: MIT License
Classifier: Operating System :: OS Independent
Classifier: Development Status :: 5 - Production/Stable
Classifier: Intended Audience :: Developers
Classifier: Intended Audience :: Science/Research
Classifier: Topic :: Software Development :: Libraries :: Python Modules
Classifier: Topic :: Scientific/Engineering :: Artificial Intelligence
Classifier: Topic :: Office/Business
Requires-Python: >=3.8
License-File: LICENSE
Requires-Dist: jmespath>=1.0.0
Requires-Dist: httpx>=0.27.0
Requires-Dist: beautifulsoup4>=4.12.0
Requires-Dist: lxml>=5.0.0
Requires-Dist: openai>=1.0.0
Requires-Dist: anthropic>=0.25.0
Requires-Dist: cryptography>=41.0.0
Requires-Dist: python-dotenv>=1.0.0
Requires-Dist: aiofiles>=23.0.0
Requires-Dist: asyncio-mqtt>=0.13.0
Dynamic: author
Dynamic: author-email
Dynamic: classifier
Dynamic: description
Dynamic: description-content-type
Dynamic: home-page
Dynamic: keywords
Dynamic: license-file
Dynamic: project-url
Dynamic: requires-dist
Dynamic: requires-python
Dynamic: summary
